setup.py
mess_srv.egg-info/PKG-INFO
mess_srv.egg-info/SOURCES.txt
mess_srv.egg-info/dependency_links.txt
mess_srv.egg-info/requires.txt
mess_srv.egg-info/top_level.txt
server/__init__.py
server/run_srv.py
server/config/__init__.py
server/config/cfg_path.py
server/config/cfg_srv_db.py
server/config/cfg_srv_logs.py
server/data/__init__.py
server/data/core.py
server/data/decorators.py
server/data/descript.py
server/data/errors.py
server/data/msg_actions.py
server/data/msg_keys.py
server/data/srv_meta.py
server/gui/__init__.py
server/gui/gui_config_window.py
server/gui/gui_main_window.py
server/gui/gui_stat_window.py
server/gui/gui_user_add.py
server/gui/gui_user_remove.py
server/logs/__init__.py
server/unit_tests/__init__.py
server/unit_tests/test_server.py