Metadata-Version: 1.0
Name: mess-srv
Version: 0.0.2
Summary: mess_srv
Home-page: UNKNOWN
Author: Sergey Semenov
Author-email: evlx@mail.ru
License: UNKNOWN
Platform: UNKNOWN
